tystyle.py
tystyle-2.0.0.dist-info/licenses/LICENSE
tystyle-2.0.0.dist-info/METADATA
tystyle-2.0.0.dist-info/WHEEL
tystyle-2.0.0.dist-info/top_level.txt
tystyle-2.0.0.dist-info/RECORD
