Metadata-Version: 2.4
Name: tystyle
Version: 2.0.0
License-File: LICENSE
Requires-Dist: rich
Dynamic: license-file
Dynamic: requires-dist
